[
  {
    "timestamp": "2025-06-14T13:39:53.350Z",
    "file": "docs/example.md",
    "action": "doc_generated",
    "size": 1017
  },
  {
    "timestamp": "2025-06-14T13:41:42.377Z",
    "file": "docs/calculator.md",
    "action": "doc_generated",
    "size": 945
  },
  {
    "timestamp": "2025-06-14T13:42:05.086Z",
    "file": "docs/calculator.md",
    "action": "doc_generated",
    "size": 946
  },
  {
    "timestamp": "2025-06-14T13:42:35.977Z",
    "file": "docs/api.md",
    "action": "doc_generated",
    "size": 935
  },
  {
    "timestamp": "2025-06-14T14:37:53.476Z",
    "file": "docs/demo-live.md",
    "action": "doc_generated",
    "size": 1007
  }
]